opentracing_compose/__init__.py
opentracing_compose-0.1.1.dist-info/LICENSE
opentracing_compose-0.1.1.dist-info/WHEEL
opentracing_compose-0.1.1.dist-info/METADATA
opentracing_compose-0.1.1.dist-info/RECORD
